gym_mcp_server/__init__.py
gym_mcp_server/__main__.py
gym_mcp_server/schemas.py
gym_mcp_server/server.py
gym_mcp_server/utils.py
gym_mcp_server-0.2.1.dist-info/METADATA
gym_mcp_server-0.2.1.dist-info/WHEEL
gym_mcp_server-0.2.1.dist-info/entry_points.txt
gym_mcp_server-0.2.1.dist-info/licenses/LICENSE
gym_mcp_server-0.2.1.dist-info/RECORD
