Metadata-Version: 2.4
Name: gym-mcp-server
Version: 0.2.1
Summary: Expose any Gymnasium environment as an MCP server
Project-URL: Homepage, https://github.com/AgentRing/gym-mcp-server
Project-URL: Repository, https://github.com/AgentRing/gym-mcp-server
Project-URL: Issues, https://github.com/AgentRing/gym-mcp-server/issues
Author: Haggai Shachar
License: MIT
License-File: LICENSE
Keywords: agents,ai,gym,gymnasium,mcp,model-context-protocol,reinforcement-learning
Classifier: Development Status :: 3 - Alpha
Classifier: Intended Audience :: Developers
Classifier: Intended Audience :: Science/Research
Classifier: License :: OSI Approved :: MIT License
Classifier: Operating System :: OS Independent
Classifier: Programming Language :: Python :: 3
Classifier: Programming Language :: Python :: 3.10
Classifier: Programming Language :: Python :: 3.11
Classifier: Programming Language :: Python :: 3.12
Classifier: Programming Language :: Python :: 3.13
Classifier: Topic :: Scientific/Engineering :: Artificial Intelligence
Classifier: Topic :: Software Development :: Libraries :: Python Modules
Requires-Python: >=3.10
Requires-Dist: gymnasium>=0.29.0
Requires-Dist: mcp>=1.0.0
Requires-Dist: numpy>=1.21.0
Requires-Dist: pillow>=8.0.0
Requires-Dist: pygame>=2.0.0
Provides-Extra: dev
Requires-Dist: black>=22.0.0; extra == 'dev'
Requires-Dist: flake8>=5.0.0; extra == 'dev'
Requires-Dist: mypy>=1.0.0; extra == 'dev'
Requires-Dist: pytest-cov>=4.0.0; extra == 'dev'
Requires-Dist: pytest>=7.0.0; extra == 'dev'
Provides-Extra: docs
Requires-Dist: sphinx-rtd-theme>=1.0.0; extra == 'docs'
Requires-Dist: sphinx>=5.0.0; extra == 'docs'
